{
  "timestamp": "2026-04-15_13-30-14",
  "update_date": "15 April 2026 13:30:14",
  "sources": {
    "GALERI 24": {
      "prices": {
        "05gr": {
          "price": "1519000",
          "buyback": "1358000"
        },
        "1gr": {
          "price": "2896000",
          "buyback": "2716000"
        },
        "2gr": {
          "price": "5721000",
          "buyback": "5432000"
        },
        "5gr": {
          "price": "14198000",
          "buyback": "13581000"
        },
        "10gr": {
          "price": "28320000",
          "buyback": "27162000"
        },
        "25gr": {
          "price": "70419000",
          "buyback": "67573000"
        },
        "50gr": {
          "price": "140727000",
          "buyback": "135147000"
        },
        "100gr": {
          "price": "281316000",
          "buyback": "270294000"
        },
        "250gr": {
          "price": "701561000",
          "buyback": "672406000"
        },
        "500gr": {
          "price": "1403121000",
          "buyback": "1344813000"
        },
        "1000gr": {
          "price": "2806240000",
          "buyback": "2689627000"
        }
      }
    },
    "ANTAM": {
      "prices": {
        "05gr": {
          "price": "1557000",
          "buyback": "1356000"
        },
        "1gr": {
          "price": "3009000",
          "buyback": "2713000"
        },
        "2gr": {
          "price": "5956000",
          "buyback": "5427000"
        },
        "3gr": {
          "price": "8907000",
          "buyback": "8140000"
        },
        "5gr": {
          "price": "14810000",
          "buyback": "13567000"
        },
        "10gr": {
          "price": "29562000",
          "buyback": "27135000"
        },
        "25gr": {
          "price": "73775000",
          "buyback": "67506000"
        },
        "50gr": {
          "price": "147467000",
          "buyback": "135012000"
        },
        "100gr": {
          "price": "294853000",
          "buyback": "270024000"
        }
      }
    },
    "UBS": {
      "prices": {
        "05gr": {
          "price": "1586000",
          "buyback": "1356000"
        },
        "1gr": {
          "price": "2934000",
          "buyback": "2713000"
        },
        "2gr": {
          "price": "5822000",
          "buyback": "5427000"
        },
        "5gr": {
          "price": "14387000",
          "buyback": "13567000"
        },
        "10gr": {
          "price": "28623000",
          "buyback": "27135000"
        },
        "25gr": {
          "price": "71416000",
          "buyback": "67506000"
        },
        "50gr": {
          "price": "142540000",
          "buyback": "135012000"
        },
        "100gr": {
          "price": "284967000",
          "buyback": "270024000"
        },
        "250gr": {
          "price": "712206000",
          "buyback": "671735000"
        },
        "500gr": {
          "price": "1422741000",
          "buyback": "1343470000"
        }
      }
    },
    "SEMAR": {
      "prices": {
        "1gr": {
          "price": "2829000",
          "buyback": "2693000"
        },
        "2gr": {
          "price": "5544000",
          "buyback": "5378000"
        },
        "3gr": {
          "price": "8316000",
          "buyback": "8109000"
        },
        "5gr": {
          "price": "13735000",
          "buyback": "13390000"
        },
        "10gr": {
          "price": "27210000",
          "buyback": "26670000"
        },
        "25gr": {
          "price": "67375000",
          "buyback": "66375000"
        },
        "50gr": {
          "price": "134750000",
          "buyback": "132750000"
        },
        "100gr": {
          "price": "269500000",
          "buyback": "265500000"
        }
      }
    }
  }
}